{
    "@context": [
        "http://api.conceptnet.io/ld/conceptnet5.6/context.ld.json"
    ], 
    "@id": "/query?node=/c/en/egg&rel=/r/CapableOf", 
    "edges": [
        {
            "@id": "/a/[/r/CapableOf/,/c/en/egg/,/c/en/break_open/]", 
            "@type": "Edge", 
            "dataset": "/d/conceptnet/4/en", 
            "end": {
                "@id": "/c/en/break_open", 
                "@type": "Node", 
                "label": "break open", 
                "language": "en", 
                "term": "/c/en/break_open"
            }, 
            "license": "cc:by/4.0", 
            "rel": {
                "@id": "/r/CapableOf", 
                "@type": "Relation", 
                "label": "CapableOf"
            }, 
            "sources": [
                {
                    "@id": "/and/[/s/activity/omcs/omcs1_possibly_free_text/,/s/contributor/omcs/quintus/]", 
                    "@type": "Source", 
                    "activity": "/s/activity/omcs/omcs1_possibly_free_text", 
                    "contributor": "/s/contributor/omcs/quintus"
                }
            ], 
            "start": {
                "@id": "/c/en/egg", 
                "@type": "Node", 
                "label": "An egg", 
                "language": "en", 
                "term": "/c/en/egg"
            }, 
            "surfaceText": "[[An egg]] can [[break open]]", 
            "weight": 1.0
        }, 
        {
            "@id": "/a/[/r/CapableOf/,/c/en/egg/,/c/en/stick_to_skillet/]", 
            "@type": "Edge", 
            "dataset": "/d/conceptnet/4/en", 
            "end": {
                "@id": "/c/en/stick_to_skillet", 
                "@type": "Node", 
                "label": "stick to a skillet", 
                "language": "en", 
                "term": "/c/en/stick_to_skillet"
            }, 
            "license": "cc:by/4.0", 
            "rel": {
                "@id": "/r/CapableOf", 
                "@type": "Relation", 
                "label": "CapableOf"
            }, 
            "sources": [
                {
                    "@id": "/and/[/s/activity/omcs/omcs1_possibly_free_text/,/s/contributor/omcs/nancyfay/]", 
                    "@type": "Source", 
                    "activity": "/s/activity/omcs/omcs1_possibly_free_text", 
                    "contributor": "/s/contributor/omcs/nancyfay"
                }
            ], 
            "start": {
                "@id": "/c/en/egg", 
                "@type": "Node", 
                "label": "an egg", 
                "language": "en", 
                "term": "/c/en/egg"
            }, 
            "surfaceText": "[[an egg]] can [[stick to a skillet]]", 
            "weight": 1.0
        }
    ]
}