{
    "@context": [
        "http://api.conceptnet.io/ld/conceptnet5.6/context.ld.json"
    ], 
    "@id": "/query?node=/c/en/handle&rel=/r/AtLocation", 
    "edges": [
        {
            "@id": "/a/[/r/AtLocation/,/c/en/handle/,/c/en/door/]", 
            "@type": "Edge", 
            "dataset": "/d/conceptnet/4/en", 
            "end": {
                "@id": "/c/en/door", 
                "@type": "Node", 
                "label": "door", 
                "language": "en", 
                "term": "/c/en/door"
            }, 
            "license": "cc:by/4.0", 
            "rel": {
                "@id": "/r/AtLocation", 
                "@type": "Relation", 
                "label": "AtLocation"
            }, 
            "sources": [
                {
                    "@id": "/and/[/s/activity/omcs/omcs1_possibly_free_text/,/s/contributor/omcs/avenger/]", 
                    "@type": "Source", 
                    "activity": "/s/activity/omcs/omcs1_possibly_free_text", 
                    "contributor": "/s/contributor/omcs/avenger"
                }, 
                {
                    "@id": "/and/[/s/activity/omcs/omcs1_possibly_free_text/,/s/contributor/omcs/rose876/]", 
                    "@type": "Source", 
                    "activity": "/s/activity/omcs/omcs1_possibly_free_text", 
                    "contributor": "/s/contributor/omcs/rose876"
                }, 
                {
                    "@id": "/and/[/s/activity/omcs/vote/,/s/contributor/omcs/avenger/]", 
                    "@type": "Source", 
                    "activity": "/s/activity/omcs/vote", 
                    "contributor": "/s/contributor/omcs/avenger"
                }
            ], 
            "start": {
                "@id": "/c/en/handle", 
                "@type": "Node", 
                "label": "a handle", 
                "language": "en", 
                "term": "/c/en/handle"
            }, 
            "surfaceText": "You are likely to find [[a handle]] in [[door]]", 
            "weight": 2.82842712474619
        }, 
        {
            "@id": "/a/[/r/AtLocation/,/c/en/handle/,/c/en/fridge/]", 
            "@type": "Edge", 
            "dataset": "/d/conceptnet/4/en", 
            "end": {
                "@id": "/c/en/fridge", 
                "@type": "Node", 
                "label": "the fridge", 
                "language": "en", 
                "term": "/c/en/fridge"
            }, 
            "license": "cc:by/4.0", 
            "rel": {
                "@id": "/r/AtLocation", 
                "@type": "Relation", 
                "label": "AtLocation"
            }, 
            "sources": [
                {
                    "@id": "/and/[/s/activity/omcs/omcs1_possibly_free_text/,/s/contributor/omcs/mbuck/]", 
                    "@type": "Source", 
                    "activity": "/s/activity/omcs/omcs1_possibly_free_text", 
                    "contributor": "/s/contributor/omcs/mbuck"
                }, 
                {
                    "@id": "/and/[/s/activity/omcs/omcs1_possibly_free_text/,/s/contributor/omcs/mhadf/]", 
                    "@type": "Source", 
                    "activity": "/s/activity/omcs/omcs1_possibly_free_text", 
                    "contributor": "/s/contributor/omcs/mhadf"
                }, 
                {
                    "@id": "/and/[/s/activity/omcs/vote/,/s/contributor/omcs/mbuck/]", 
                    "@type": "Source", 
                    "activity": "/s/activity/omcs/vote", 
                    "contributor": "/s/contributor/omcs/mbuck"
                }
            ], 
            "start": {
                "@id": "/c/en/handle", 
                "@type": "Node", 
                "label": "a handle", 
                "language": "en", 
                "term": "/c/en/handle"
            }, 
            "surfaceText": "*Something you find in [[the fridge]] is [[a handle]]", 
            "weight": 2.82842712474619
        }, 
        {
            "@id": "/a/[/r/AtLocation/,/c/en/handle/,/c/en/bathroom/]", 
            "@type": "Edge", 
            "dataset": "/d/conceptnet/4/en", 
            "end": {
                "@id": "/c/en/bathroom", 
                "@type": "Node", 
                "label": "the bathroom", 
                "language": "en", 
                "term": "/c/en/bathroom"
            }, 
            "license": "cc:by/4.0", 
            "rel": {
                "@id": "/r/AtLocation", 
                "@type": "Relation", 
                "label": "AtLocation"
            }, 
            "sources": [
                {
                    "@id": "/and/[/s/activity/omcs/omcs1_possibly_free_text/,/s/contributor/omcs/zenith/]", 
                    "@type": "Source", 
                    "activity": "/s/activity/omcs/omcs1_possibly_free_text", 
                    "contributor": "/s/contributor/omcs/zenith"
                }
            ], 
            "start": {
                "@id": "/c/en/handle", 
                "@type": "Node", 
                "label": "a handle", 
                "language": "en", 
                "term": "/c/en/handle"
            }, 
            "surfaceText": "You are likely to find [[a handle]] in [[the bathroom]]", 
            "weight": 1.0
        }, 
        {
            "@id": "/a/[/r/AtLocation/,/c/en/handle/,/c/en/car_door/]", 
            "@type": "Edge", 
            "dataset": "/d/conceptnet/4/en", 
            "end": {
                "@id": "/c/en/car_door", 
                "@type": "Node", 
                "label": "a car door", 
                "language": "en", 
                "term": "/c/en/car_door"
            }, 
            "license": "cc:by/4.0", 
            "rel": {
                "@id": "/r/AtLocation", 
                "@type": "Relation", 
                "label": "AtLocation"
            }, 
            "sources": [
                {
                    "@id": "/and/[/s/activity/omcs/omcs1_possibly_free_text/,/s/contributor/omcs/katie/]", 
                    "@type": "Source", 
                    "activity": "/s/activity/omcs/omcs1_possibly_free_text", 
                    "contributor": "/s/contributor/omcs/katie"
                }
            ], 
            "start": {
                "@id": "/c/en/handle", 
                "@type": "Node", 
                "label": "a handle", 
                "language": "en", 
                "term": "/c/en/handle"
            }, 
            "surfaceText": "You are likely to find [[a handle]] in [[a car door]]", 
            "weight": 1.0
        }, 
        {
            "@id": "/a/[/r/AtLocation/,/c/en/handle/,/c/en/drawer/]", 
            "@type": "Edge", 
            "dataset": "/d/conceptnet/4/en", 
            "end": {
                "@id": "/c/en/drawer", 
                "@type": "Node", 
                "label": "a drawer", 
                "language": "en", 
                "term": "/c/en/drawer"
            }, 
            "license": "cc:by/4.0", 
            "rel": {
                "@id": "/r/AtLocation", 
                "@type": "Relation", 
                "label": "AtLocation"
            }, 
            "sources": [
                {
                    "@id": "/and/[/s/activity/omcs/omcs1_possibly_free_text/,/s/contributor/omcs/anaitis/]", 
                    "@type": "Source", 
                    "activity": "/s/activity/omcs/omcs1_possibly_free_text", 
                    "contributor": "/s/contributor/omcs/anaitis"
                }
            ], 
            "start": {
                "@id": "/c/en/handle", 
                "@type": "Node", 
                "label": "a handle", 
                "language": "en", 
                "term": "/c/en/handle"
            }, 
            "surfaceText": "You are likely to find [[a handle]] in [[a drawer]]", 
            "weight": 1.0
        }, 
        {
            "@id": "/a/[/r/AtLocation/,/c/en/handle/,/c/en/hardware_store/]", 
            "@type": "Edge", 
            "dataset": "/d/conceptnet/4/en", 
            "end": {
                "@id": "/c/en/hardware_store", 
                "@type": "Node", 
                "label": "a hardware store", 
                "language": "en", 
                "term": "/c/en/hardware_store"
            }, 
            "license": "cc:by/4.0", 
            "rel": {
                "@id": "/r/AtLocation", 
                "@type": "Relation", 
                "label": "AtLocation"
            }, 
            "sources": [
                {
                    "@id": "/and/[/s/activity/omcs/omcs1_possibly_free_text/,/s/contributor/omcs/socrates/]", 
                    "@type": "Source", 
                    "activity": "/s/activity/omcs/omcs1_possibly_free_text", 
                    "contributor": "/s/contributor/omcs/socrates"
                }
            ], 
            "start": {
                "@id": "/c/en/handle", 
                "@type": "Node", 
                "label": "a handle", 
                "language": "en", 
                "term": "/c/en/handle"
            }, 
            "surfaceText": "You are likely to find [[a handle]] in [[a hardware store]]", 
            "weight": 1.0
        }, 
        {
            "@id": "/a/[/r/AtLocation/,/c/en/handle/,/c/en/water_fountain/]", 
            "@type": "Edge", 
            "dataset": "/d/conceptnet/4/en", 
            "end": {
                "@id": "/c/en/water_fountain", 
                "@type": "Node", 
                "label": "a water fountain", 
                "language": "en", 
                "term": "/c/en/water_fountain"
            }, 
            "license": "cc:by/4.0", 
            "rel": {
                "@id": "/r/AtLocation", 
                "@type": "Relation", 
                "label": "AtLocation"
            }, 
            "sources": [
                {
                    "@id": "/and/[/s/activity/omcs/omcs1_possibly_free_text/,/s/contributor/omcs/pellart/]", 
                    "@type": "Source", 
                    "activity": "/s/activity/omcs/omcs1_possibly_free_text", 
                    "contributor": "/s/contributor/omcs/pellart"
                }
            ], 
            "start": {
                "@id": "/c/en/handle", 
                "@type": "Node", 
                "label": "a handle", 
                "language": "en", 
                "term": "/c/en/handle"
            }, 
            "surfaceText": "*Something you find at [[a water fountain]] is [[a handle]]", 
            "weight": 1.0
        }
    ]
}