{
    "@context": [
        "http://api.conceptnet.io/ld/conceptnet5.6/context.ld.json"
    ], 
    "@id": "/query?node=/c/en/ottoman&rel=/r/UsedFor", 
    "edges": [
        {
            "@id": "/a/[/r/UsedFor/,/c/en/ottoman/,/c/en/sitting/]", 
            "@type": "Edge", 
            "dataset": "/d/conceptnet/4/en", 
            "end": {
                "@id": "/c/en/sitting", 
                "@type": "Node", 
                "label": "sitting", 
                "language": "en", 
                "term": "/c/en/sitting"
            }, 
            "license": "cc:by/4.0", 
            "rel": {
                "@id": "/r/UsedFor", 
                "@type": "Relation", 
                "label": "UsedFor"
            }, 
            "sources": [
                {
                    "@id": "/and/[/s/activity/omcs/omcs1_possibly_free_text/,/s/contributor/omcs/laserjoy/]", 
                    "@type": "Source", 
                    "activity": "/s/activity/omcs/omcs1_possibly_free_text", 
                    "contributor": "/s/contributor/omcs/laserjoy"
                }, 
                {
                    "@id": "/and/[/s/activity/omcs/vote/,/s/contributor/omcs/gamma625/]", 
                    "@type": "Source", 
                    "activity": "/s/activity/omcs/vote", 
                    "contributor": "/s/contributor/omcs/gamma625"
                }, 
                {
                    "@id": "/and/[/s/activity/omcs/vote/,/s/contributor/omcs/openpod/]", 
                    "@type": "Source", 
                    "activity": "/s/activity/omcs/vote", 
                    "contributor": "/s/contributor/omcs/openpod"
                }, 
                {
                    "@id": "/and/[/s/activity/omcs/vote/,/s/contributor/omcs/xerolooper/]", 
                    "@type": "Source", 
                    "activity": "/s/activity/omcs/vote", 
                    "contributor": "/s/contributor/omcs/xerolooper"
                }
            ], 
            "start": {
                "@id": "/c/en/ottoman", 
                "@type": "Node", 
                "label": "an ottoman", 
                "language": "en", 
                "term": "/c/en/ottoman"
            }, 
            "surfaceText": "[[an ottoman]] is used for [[sitting]]", 
            "weight": 3.4641016151377544
        }, 
        {
            "@id": "/a/[/r/UsedFor/,/c/en/ottoman/,/c/en/put_feet_on/]", 
            "@type": "Edge", 
            "dataset": "/d/conceptnet/4/en", 
            "end": {
                "@id": "/c/en/put_feet_on", 
                "@type": "Node", 
                "label": "put your feet on", 
                "language": "en", 
                "term": "/c/en/put_feet_on"
            }, 
            "license": "cc:by/4.0", 
            "rel": {
                "@id": "/r/UsedFor", 
                "@type": "Relation", 
                "label": "UsedFor"
            }, 
            "sources": [
                {
                    "@id": "/and/[/s/activity/omcs/omcs1_possibly_free_text/,/s/contributor/omcs/cobalt71/]", 
                    "@type": "Source", 
                    "activity": "/s/activity/omcs/omcs1_possibly_free_text", 
                    "contributor": "/s/contributor/omcs/cobalt71"
                }, 
                {
                    "@id": "/and/[/s/activity/omcs/vote/,/s/contributor/omcs/chotchki/]", 
                    "@type": "Source", 
                    "activity": "/s/activity/omcs/vote", 
                    "contributor": "/s/contributor/omcs/chotchki"
                }, 
                {
                    "@id": "/and/[/s/activity/omcs/vote/,/s/contributor/omcs/dbn3/]", 
                    "@type": "Source", 
                    "activity": "/s/activity/omcs/vote", 
                    "contributor": "/s/contributor/omcs/dbn3"
                }
            ], 
            "start": {
                "@id": "/c/en/ottoman", 
                "@type": "Node", 
                "label": "an ottoman", 
                "language": "en", 
                "term": "/c/en/ottoman"
            }, 
            "surfaceText": "You can use [[an ottoman]] to [[put your feet on]]", 
            "weight": 2.82842712474619
        }, 
        {
            "@id": "/a/[/r/UsedFor/,/c/en/ottoman/,/c/en/prop_feet/]", 
            "@type": "Edge", 
            "dataset": "/d/conceptnet/4/en", 
            "end": {
                "@id": "/c/en/prop_feet", 
                "@type": "Node", 
                "label": "prop feet", 
                "language": "en", 
                "term": "/c/en/prop_feet"
            }, 
            "license": "cc:by/4.0", 
            "rel": {
                "@id": "/r/UsedFor", 
                "@type": "Relation", 
                "label": "UsedFor"
            }, 
            "sources": [
                {
                    "@id": "/and/[/s/activity/omcs/omcs1_possibly_free_text/,/s/contributor/omcs/laserjoy/]", 
                    "@type": "Source", 
                    "activity": "/s/activity/omcs/omcs1_possibly_free_text", 
                    "contributor": "/s/contributor/omcs/laserjoy"
                }, 
                {
                    "@id": "/and/[/s/activity/omcs/vote/,/s/contributor/omcs/brainsofsteel/]", 
                    "@type": "Source", 
                    "activity": "/s/activity/omcs/vote", 
                    "contributor": "/s/contributor/omcs/brainsofsteel"
                }
            ], 
            "start": {
                "@id": "/c/en/ottoman", 
                "@type": "Node", 
                "label": "an ottoman", 
                "language": "en", 
                "term": "/c/en/ottoman"
            }, 
            "surfaceText": "You can use [[an ottoman]] to [[prop feet]]", 
            "weight": 2.0
        }, 
        {
            "@id": "/a/[/r/UsedFor/,/c/en/ottoman/,/c/en/rest_feet/]", 
            "@type": "Edge", 
            "dataset": "/d/conceptnet/4/en", 
            "end": {
                "@id": "/c/en/rest_feet", 
                "@type": "Node", 
                "label": "rest your feet", 
                "language": "en", 
                "term": "/c/en/rest_feet"
            }, 
            "license": "cc:by/4.0", 
            "rel": {
                "@id": "/r/UsedFor", 
                "@type": "Relation", 
                "label": "UsedFor"
            }, 
            "sources": [
                {
                    "@id": "/and/[/s/activity/omcs/omcs1_possibly_free_text/,/s/contributor/omcs/femto/]", 
                    "@type": "Source", 
                    "activity": "/s/activity/omcs/omcs1_possibly_free_text", 
                    "contributor": "/s/contributor/omcs/femto"
                }, 
                {
                    "@id": "/and/[/s/activity/omcs/vote/,/s/contributor/omcs/debhotmac/]", 
                    "@type": "Source", 
                    "activity": "/s/activity/omcs/vote", 
                    "contributor": "/s/contributor/omcs/debhotmac"
                }
            ], 
            "start": {
                "@id": "/c/en/ottoman", 
                "@type": "Node", 
                "label": "an ottoman", 
                "language": "en", 
                "term": "/c/en/ottoman"
            }, 
            "surfaceText": "You can use [[an ottoman]] to [[rest your feet]]", 
            "weight": 2.0
        }, 
        {
            "@id": "/a/[/r/UsedFor/,/c/en/ottoman/,/c/en/decoration/]", 
            "@type": "Edge", 
            "dataset": "/d/conceptnet/4/en", 
            "end": {
                "@id": "/c/en/decoration", 
                "@type": "Node", 
                "label": "decoration", 
                "language": "en", 
                "term": "/c/en/decoration"
            }, 
            "license": "cc:by/4.0", 
            "rel": {
                "@id": "/r/UsedFor", 
                "@type": "Relation", 
                "label": "UsedFor"
            }, 
            "sources": [
                {
                    "@id": "/and/[/s/activity/omcs/omcs1_possibly_free_text/,/s/contributor/omcs/laserjoy/]", 
                    "@type": "Source", 
                    "activity": "/s/activity/omcs/omcs1_possibly_free_text", 
                    "contributor": "/s/contributor/omcs/laserjoy"
                }
            ], 
            "start": {
                "@id": "/c/en/ottoman", 
                "@type": "Node", 
                "label": "an ottoman", 
                "language": "en", 
                "term": "/c/en/ottoman"
            }, 
            "surfaceText": "[[an ottoman]] is used for [[decoration]]", 
            "weight": 1.0
        }, 
        {
            "@id": "/a/[/r/UsedFor/,/c/en/ottoman/,/c/en/prop_up_feet/]", 
            "@type": "Edge", 
            "dataset": "/d/conceptnet/4/en", 
            "end": {
                "@id": "/c/en/prop_up_feet", 
                "@type": "Node", 
                "label": "prop up your feet", 
                "language": "en", 
                "term": "/c/en/prop_up_feet"
            }, 
            "license": "cc:by/4.0", 
            "rel": {
                "@id": "/r/UsedFor", 
                "@type": "Relation", 
                "label": "UsedFor"
            }, 
            "sources": [
                {
                    "@id": "/and/[/s/activity/omcs/omcs1_possibly_free_text/,/s/contributor/omcs/brainsofsteel/]", 
                    "@type": "Source", 
                    "activity": "/s/activity/omcs/omcs1_possibly_free_text", 
                    "contributor": "/s/contributor/omcs/brainsofsteel"
                }
            ], 
            "start": {
                "@id": "/c/en/ottoman", 
                "@type": "Node", 
                "label": "an ottoman", 
                "language": "en", 
                "term": "/c/en/ottoman"
            }, 
            "surfaceText": "You can use [[an ottoman]] to [[prop up your feet]]", 
            "weight": 1.0
        }, 
        {
            "@id": "/a/[/r/UsedFor/,/c/en/ottoman/,/c/en/put_feet_up/]", 
            "@type": "Edge", 
            "dataset": "/d/conceptnet/4/en", 
            "end": {
                "@id": "/c/en/put_feet_up", 
                "@type": "Node", 
                "label": "put your feet up", 
                "language": "en", 
                "term": "/c/en/put_feet_up"
            }, 
            "license": "cc:by/4.0", 
            "rel": {
                "@id": "/r/UsedFor", 
                "@type": "Relation", 
                "label": "UsedFor"
            }, 
            "sources": [
                {
                    "@id": "/and/[/s/activity/omcs/omcs1_possibly_free_text/,/s/contributor/omcs/dbn3/]", 
                    "@type": "Source", 
                    "activity": "/s/activity/omcs/omcs1_possibly_free_text", 
                    "contributor": "/s/contributor/omcs/dbn3"
                }
            ], 
            "start": {
                "@id": "/c/en/ottoman", 
                "@type": "Node", 
                "label": "an ottoman", 
                "language": "en", 
                "term": "/c/en/ottoman"
            }, 
            "surfaceText": "You can use [[an ottoman]] to [[put your feet up]]", 
            "weight": 1.0
        }, 
        {
            "@id": "/a/[/r/UsedFor/,/c/en/ottoman/,/c/en/put_feet_up_and_relax/]", 
            "@type": "Edge", 
            "dataset": "/d/conceptnet/4/en", 
            "end": {
                "@id": "/c/en/put_feet_up_and_relax", 
                "@type": "Node", 
                "label": "put your feet up and relax", 
                "language": "en", 
                "term": "/c/en/put_feet_up_and_relax"
            }, 
            "license": "cc:by/4.0", 
            "rel": {
                "@id": "/r/UsedFor", 
                "@type": "Relation", 
                "label": "UsedFor"
            }, 
            "sources": [
                {
                    "@id": "/and/[/s/activity/omcs/omcs1_possibly_free_text/,/s/contributor/omcs/annedog/]", 
                    "@type": "Source", 
                    "activity": "/s/activity/omcs/omcs1_possibly_free_text", 
                    "contributor": "/s/contributor/omcs/annedog"
                }
            ], 
            "start": {
                "@id": "/c/en/ottoman", 
                "@type": "Node", 
                "label": "an ottoman", 
                "language": "en", 
                "term": "/c/en/ottoman"
            }, 
            "surfaceText": "You can use [[an ottoman]] to [[put your feet up and relax]]", 
            "weight": 1.0
        }, 
        {
            "@id": "/a/[/r/UsedFor/,/c/en/ottoman/,/c/en/raising_up_feet/]", 
            "@type": "Edge", 
            "dataset": "/d/conceptnet/4/en", 
            "end": {
                "@id": "/c/en/raising_up_feet", 
                "@type": "Node", 
                "label": "raising up feet", 
                "language": "en", 
                "term": "/c/en/raising_up_feet"
            }, 
            "license": "cc:by/4.0", 
            "rel": {
                "@id": "/r/UsedFor", 
                "@type": "Relation", 
                "label": "UsedFor"
            }, 
            "sources": [
                {
                    "@id": "/and/[/s/activity/omcs/omcs1_possibly_free_text/,/s/contributor/omcs/laserjoy/]", 
                    "@type": "Source", 
                    "activity": "/s/activity/omcs/omcs1_possibly_free_text", 
                    "contributor": "/s/contributor/omcs/laserjoy"
                }
            ], 
            "start": {
                "@id": "/c/en/ottoman", 
                "@type": "Node", 
                "label": "an ottoman", 
                "language": "en", 
                "term": "/c/en/ottoman"
            }, 
            "surfaceText": "[[an ottoman]] is used for [[raising up feet]]", 
            "weight": 1.0
        }, 
        {
            "@id": "/a/[/r/UsedFor/,/c/en/ottoman/,/c/en/reclining_legs/]", 
            "@type": "Edge", 
            "dataset": "/d/conceptnet/4/en", 
            "end": {
                "@id": "/c/en/reclining_legs", 
                "@type": "Node", 
                "label": "reclining your legs", 
                "language": "en", 
                "term": "/c/en/reclining_legs"
            }, 
            "license": "cc:by/4.0", 
            "rel": {
                "@id": "/r/UsedFor", 
                "@type": "Relation", 
                "label": "UsedFor"
            }, 
            "sources": [
                {
                    "@id": "/and/[/s/activity/omcs/omcs1_possibly_free_text/,/s/contributor/omcs/phraughy/]", 
                    "@type": "Source", 
                    "activity": "/s/activity/omcs/omcs1_possibly_free_text", 
                    "contributor": "/s/contributor/omcs/phraughy"
                }
            ], 
            "start": {
                "@id": "/c/en/ottoman", 
                "@type": "Node", 
                "label": "an ottoman", 
                "language": "en", 
                "term": "/c/en/ottoman"
            }, 
            "surfaceText": "[[an ottoman]] is for [[reclining your legs]]", 
            "weight": 1.0
        }, 
        {
            "@id": "/a/[/r/UsedFor/,/c/en/ottoman/,/c/en/relaxing/]", 
            "@type": "Edge", 
            "dataset": "/d/conceptnet/4/en", 
            "end": {
                "@id": "/c/en/relaxing", 
                "@type": "Node", 
                "label": "relaxing", 
                "language": "en", 
                "term": "/c/en/relaxing"
            }, 
            "license": "cc:by/4.0", 
            "rel": {
                "@id": "/r/UsedFor", 
                "@type": "Relation", 
                "label": "UsedFor"
            }, 
            "sources": [
                {
                    "@id": "/and/[/s/activity/omcs/omcs1_possibly_free_text/,/s/contributor/omcs/dvanhoozer/]", 
                    "@type": "Source", 
                    "activity": "/s/activity/omcs/omcs1_possibly_free_text", 
                    "contributor": "/s/contributor/omcs/dvanhoozer"
                }
            ], 
            "start": {
                "@id": "/c/en/ottoman", 
                "@type": "Node", 
                "label": "an ottoman", 
                "language": "en", 
                "term": "/c/en/ottoman"
            }, 
            "surfaceText": "[[an ottoman]] is used for [[relaxing]]", 
            "weight": 1.0
        }, 
        {
            "@id": "/a/[/r/UsedFor/,/c/en/ottoman/,/c/en/resting_feet/]", 
            "@type": "Edge", 
            "dataset": "/d/conceptnet/4/en", 
            "end": {
                "@id": "/c/en/resting_feet", 
                "@type": "Node", 
                "label": "resting your feet", 
                "language": "en", 
                "term": "/c/en/resting_feet"
            }, 
            "license": "cc:by/4.0", 
            "rel": {
                "@id": "/r/UsedFor", 
                "@type": "Relation", 
                "label": "UsedFor"
            }, 
            "sources": [
                {
                    "@id": "/and/[/s/activity/omcs/omcs1_possibly_free_text/,/s/contributor/omcs/debhotmac/]", 
                    "@type": "Source", 
                    "activity": "/s/activity/omcs/omcs1_possibly_free_text", 
                    "contributor": "/s/contributor/omcs/debhotmac"
                }
            ], 
            "start": {
                "@id": "/c/en/ottoman", 
                "@type": "Node", 
                "label": "an ottoman", 
                "language": "en", 
                "term": "/c/en/ottoman"
            }, 
            "surfaceText": "[[an ottoman]] is used for [[resting your feet]]", 
            "weight": 1.0
        }, 
        {
            "@id": "/a/[/r/UsedFor/,/c/en/ottoman/,/c/en/sit/]", 
            "@type": "Edge", 
            "dataset": "/d/conceptnet/4/en", 
            "end": {
                "@id": "/c/en/sit", 
                "@type": "Node", 
                "label": "sit", 
                "language": "en", 
                "term": "/c/en/sit"
            }, 
            "license": "cc:by/4.0", 
            "rel": {
                "@id": "/r/UsedFor", 
                "@type": "Relation", 
                "label": "UsedFor"
            }, 
            "sources": [
                {
                    "@id": "/and/[/s/activity/omcs/omcs1_possibly_free_text/,/s/contributor/omcs/xerolooper/]", 
                    "@type": "Source", 
                    "activity": "/s/activity/omcs/omcs1_possibly_free_text", 
                    "contributor": "/s/contributor/omcs/xerolooper"
                }
            ], 
            "start": {
                "@id": "/c/en/ottoman", 
                "@type": "Node", 
                "label": "an ottoman", 
                "language": "en", 
                "term": "/c/en/ottoman"
            }, 
            "surfaceText": "You can use [[an ottoman]] to [[sit]]", 
            "weight": 1.0
        }, 
        {
            "@id": "/a/[/r/UsedFor/,/c/en/ottoman/,/c/en/sit_down/]", 
            "@type": "Edge", 
            "dataset": "/d/conceptnet/4/en", 
            "end": {
                "@id": "/c/en/sit_down", 
                "@type": "Node", 
                "label": "sit down", 
                "language": "en", 
                "term": "/c/en/sit_down"
            }, 
            "license": "cc:by/4.0", 
            "rel": {
                "@id": "/r/UsedFor", 
                "@type": "Relation", 
                "label": "UsedFor"
            }, 
            "sources": [
                {
                    "@id": "/and/[/s/activity/omcs/omcs1_possibly_free_text/,/s/contributor/omcs/gamma625/]", 
                    "@type": "Source", 
                    "activity": "/s/activity/omcs/omcs1_possibly_free_text", 
                    "contributor": "/s/contributor/omcs/gamma625"
                }
            ], 
            "start": {
                "@id": "/c/en/ottoman", 
                "@type": "Node", 
                "label": "an ottoman", 
                "language": "en", 
                "term": "/c/en/ottoman"
            }, 
            "surfaceText": "You can use [[an ottoman]] to [[sit down]]", 
            "weight": 1.0
        }, 
        {
            "@id": "/a/[/r/UsedFor/,/c/en/ottoman/,/c/en/sit_on/]", 
            "@type": "Edge", 
            "dataset": "/d/conceptnet/4/en", 
            "end": {
                "@id": "/c/en/sit_on", 
                "@type": "Node", 
                "label": "sit on", 
                "language": "en", 
                "term": "/c/en/sit_on"
            }, 
            "license": "cc:by/4.0", 
            "rel": {
                "@id": "/r/UsedFor", 
                "@type": "Relation", 
                "label": "UsedFor"
            }, 
            "sources": [
                {
                    "@id": "/and/[/s/activity/omcs/omcs1_possibly_free_text/,/s/contributor/omcs/openpod/]", 
                    "@type": "Source", 
                    "activity": "/s/activity/omcs/omcs1_possibly_free_text", 
                    "contributor": "/s/contributor/omcs/openpod"
                }
            ], 
            "start": {
                "@id": "/c/en/ottoman", 
                "@type": "Node", 
                "label": "an ottoman", 
                "language": "en", 
                "term": "/c/en/ottoman"
            }, 
            "surfaceText": "You can use [[an ottoman]] to [[sit on]]", 
            "weight": 1.0
        }, 
        {
            "@id": "/a/[/r/UsedFor/,/c/en/ottoman/,/c/en/take_nap/]", 
            "@type": "Edge", 
            "dataset": "/d/conceptnet/4/en", 
            "end": {
                "@id": "/c/en/take_nap", 
                "@type": "Node", 
                "label": "take a nap", 
                "language": "en", 
                "term": "/c/en/take_nap"
            }, 
            "license": "cc:by/4.0", 
            "rel": {
                "@id": "/r/UsedFor", 
                "@type": "Relation", 
                "label": "UsedFor"
            }, 
            "sources": [
                {
                    "@id": "/and/[/s/activity/omcs/omcs1_possibly_free_text/,/s/contributor/omcs/twospooky/]", 
                    "@type": "Source", 
                    "activity": "/s/activity/omcs/omcs1_possibly_free_text", 
                    "contributor": "/s/contributor/omcs/twospooky"
                }
            ], 
            "start": {
                "@id": "/c/en/ottoman", 
                "@type": "Node", 
                "label": "an ottoman", 
                "language": "en", 
                "term": "/c/en/ottoman"
            }, 
            "surfaceText": "You can use [[an ottoman]] to [[take a nap]]", 
            "weight": 1.0
        }
    ]
}