{
    "@context": [
        "http://api.conceptnet.io/ld/conceptnet5.6/context.ld.json"
    ], 
    "@id": "/query?node=/c/en/scissors&rel=/r/CapableOf", 
    "edges": [
        {
            "@id": "/a/[/r/CapableOf/,/c/en/scissors/,/c/en/cut_paper/]", 
            "@type": "Edge", 
            "dataset": "/d/conceptnet/4/en", 
            "end": {
                "@id": "/c/en/cut_paper", 
                "@type": "Node", 
                "label": "cut that paper", 
                "language": "en", 
                "term": "/c/en/cut_paper"
            }, 
            "license": "cc:by/4.0", 
            "rel": {
                "@id": "/r/CapableOf", 
                "@type": "Relation", 
                "label": "CapableOf"
            }, 
            "sources": [
                {
                    "@id": "/and/[/s/activity/omcs/omcs1_possibly_free_text/,/s/contributor/omcs/lainxiii/]", 
                    "@type": "Source", 
                    "activity": "/s/activity/omcs/omcs1_possibly_free_text", 
                    "contributor": "/s/contributor/omcs/lainxiii"
                }, 
                {
                    "@id": "/and/[/s/activity/omcs/omcs1_possibly_free_text/,/s/contributor/omcs/magnificat/]", 
                    "@type": "Source", 
                    "activity": "/s/activity/omcs/omcs1_possibly_free_text", 
                    "contributor": "/s/contributor/omcs/magnificat"
                }, 
                {
                    "@id": "/and/[/s/activity/omcs/omcs1_possibly_free_text/,/s/contributor/omcs/plees/]", 
                    "@type": "Source", 
                    "activity": "/s/activity/omcs/omcs1_possibly_free_text", 
                    "contributor": "/s/contributor/omcs/plees"
                }, 
                {
                    "@id": "/and/[/s/activity/omcs/vote/,/s/contributor/omcs/ariadne/]", 
                    "@type": "Source", 
                    "activity": "/s/activity/omcs/vote", 
                    "contributor": "/s/contributor/omcs/ariadne"
                }, 
                {
                    "@id": "/and/[/s/activity/omcs/vote/,/s/contributor/omcs/magnificat/]", 
                    "@type": "Source", 
                    "activity": "/s/activity/omcs/vote", 
                    "contributor": "/s/contributor/omcs/magnificat"
                }, 
                {
                    "@id": "/and/[/s/activity/omcs/vote/,/s/contributor/omcs/phraughy/]", 
                    "@type": "Source", 
                    "activity": "/s/activity/omcs/vote", 
                    "contributor": "/s/contributor/omcs/phraughy"
                }, 
                {
                    "@id": "/and/[/s/activity/omcs/vote/,/s/contributor/omcs/plees/]", 
                    "@type": "Source", 
                    "activity": "/s/activity/omcs/vote", 
                    "contributor": "/s/contributor/omcs/plees"
                }
            ], 
            "start": {
                "@id": "/c/en/scissors", 
                "@type": "Node", 
                "label": "scissors", 
                "language": "en", 
                "term": "/c/en/scissors"
            }, 
            "surfaceText": "[[scissors]] can [[cut that paper]]", 
            "weight": 5.291502622129181
        }, 
        {
            "@id": "/a/[/r/CapableOf/,/c/en/scissors/,/c/en/become_blunt/]", 
            "@type": "Edge", 
            "dataset": "/d/conceptnet/4/en", 
            "end": {
                "@id": "/c/en/become_blunt", 
                "@type": "Node", 
                "label": "become blunt", 
                "language": "en", 
                "term": "/c/en/become_blunt"
            }, 
            "license": "cc:by/4.0", 
            "rel": {
                "@id": "/r/CapableOf", 
                "@type": "Relation", 
                "label": "CapableOf"
            }, 
            "sources": [
                {
                    "@id": "/and/[/s/activity/omcs/omcs1_possibly_free_text/,/s/contributor/omcs/cfalz/]", 
                    "@type": "Source", 
                    "activity": "/s/activity/omcs/omcs1_possibly_free_text", 
                    "contributor": "/s/contributor/omcs/cfalz"
                }
            ], 
            "start": {
                "@id": "/c/en/scissors", 
                "@type": "Node", 
                "label": "scissors", 
                "language": "en", 
                "term": "/c/en/scissors"
            }, 
            "surfaceText": "[[scissors]] can [[become blunt]]", 
            "weight": 1.0
        }, 
        {
            "@id": "/a/[/r/CapableOf/,/c/en/scissors/,/c/en/cut_cardboard/]", 
            "@type": "Edge", 
            "dataset": "/d/conceptnet/4/en", 
            "end": {
                "@id": "/c/en/cut_cardboard", 
                "@type": "Node", 
                "label": "cut cardboard", 
                "language": "en", 
                "term": "/c/en/cut_cardboard"
            }, 
            "license": "cc:by/4.0", 
            "rel": {
                "@id": "/r/CapableOf", 
                "@type": "Relation", 
                "label": "CapableOf"
            }, 
            "sources": [
                {
                    "@id": "/and/[/s/activity/omcs/omcs1_possibly_free_text/,/s/contributor/omcs/jstearns/]", 
                    "@type": "Source", 
                    "activity": "/s/activity/omcs/omcs1_possibly_free_text", 
                    "contributor": "/s/contributor/omcs/jstearns"
                }
            ], 
            "start": {
                "@id": "/c/en/scissors", 
                "@type": "Node", 
                "label": "scissors", 
                "language": "en", 
                "term": "/c/en/scissors"
            }, 
            "surfaceText": "[[scissors]] can [[cut cardboard]]", 
            "weight": 1.0
        }, 
        {
            "@id": "/a/[/r/CapableOf/,/c/en/scissors/,/c/en/part_paper/]", 
            "@type": "Edge", 
            "dataset": "/d/conceptnet/4/en", 
            "end": {
                "@id": "/c/en/part_paper", 
                "@type": "Node", 
                "label": "part paper", 
                "language": "en", 
                "term": "/c/en/part_paper"
            }, 
            "license": "cc:by/4.0", 
            "rel": {
                "@id": "/r/CapableOf", 
                "@type": "Relation", 
                "label": "CapableOf"
            }, 
            "sources": [
                {
                    "@id": "/and/[/s/activity/omcs/omcs1_possibly_free_text/,/s/contributor/omcs/sharkd/]", 
                    "@type": "Source", 
                    "activity": "/s/activity/omcs/omcs1_possibly_free_text", 
                    "contributor": "/s/contributor/omcs/sharkd"
                }
            ], 
            "start": {
                "@id": "/c/en/scissors", 
                "@type": "Node", 
                "label": "scissors", 
                "language": "en", 
                "term": "/c/en/scissors"
            }, 
            "surfaceText": "[[scissors]] can [[part paper]]", 
            "weight": 1.0
        }, 
        {
            "@id": "/a/[/r/CapableOf/,/c/en/scissors/,/c/en/tear_cloth/]", 
            "@type": "Edge", 
            "dataset": "/d/conceptnet/4/en", 
            "end": {
                "@id": "/c/en/tear_cloth", 
                "@type": "Node", 
                "label": "tear cloth", 
                "language": "en", 
                "term": "/c/en/tear_cloth"
            }, 
            "license": "cc:by/4.0", 
            "rel": {
                "@id": "/r/CapableOf", 
                "@type": "Relation", 
                "label": "CapableOf"
            }, 
            "sources": [
                {
                    "@id": "/and/[/s/activity/omcs/omcs1_possibly_free_text/,/s/contributor/omcs/neuromancer/]", 
                    "@type": "Source", 
                    "activity": "/s/activity/omcs/omcs1_possibly_free_text", 
                    "contributor": "/s/contributor/omcs/neuromancer"
                }
            ], 
            "start": {
                "@id": "/c/en/scissors", 
                "@type": "Node", 
                "label": "scissors", 
                "language": "en", 
                "term": "/c/en/scissors"
            }, 
            "surfaceText": "[[scissors]] can [[tear cloth]]", 
            "weight": 1.0
        }, 
        {
            "@id": "/a/[/r/CapableOf/,/c/en/scissors/,/c/en/tear_paper/]", 
            "@type": "Edge", 
            "dataset": "/d/conceptnet/4/en", 
            "end": {
                "@id": "/c/en/tear_paper", 
                "@type": "Node", 
                "label": "tear paper", 
                "language": "en", 
                "term": "/c/en/tear_paper"
            }, 
            "license": "cc:by/4.0", 
            "rel": {
                "@id": "/r/CapableOf", 
                "@type": "Relation", 
                "label": "CapableOf"
            }, 
            "sources": [
                {
                    "@id": "/and/[/s/activity/omcs/omcs1_possibly_free_text/,/s/contributor/omcs/flyboi2003/]", 
                    "@type": "Source", 
                    "activity": "/s/activity/omcs/omcs1_possibly_free_text", 
                    "contributor": "/s/contributor/omcs/flyboi2003"
                }
            ], 
            "start": {
                "@id": "/c/en/scissors", 
                "@type": "Node", 
                "label": "scissors", 
                "language": "en", 
                "term": "/c/en/scissors"
            }, 
            "surfaceText": "[[scissors]] can [[tear paper]]", 
            "weight": 1.0
        }
    ]
}