{
    "@context": [
        "http://api.conceptnet.io/ld/conceptnet5.6/context.ld.json"
    ], 
    "@id": "/query?node=/c/en/umbrella_stand&rel=/r/AtLocation", 
    "edges": [
        {
            "@id": "/a/[/r/AtLocation/,/c/en/umbrella/,/c/en/umbrella_stand/]", 
            "@type": "Edge", 
            "dataset": "/d/conceptnet/4/en", 
            "end": {
                "@id": "/c/en/umbrella_stand", 
                "@type": "Node", 
                "label": "an umbrella stand", 
                "language": "en", 
                "term": "/c/en/umbrella_stand"
            }, 
            "license": "cc:by/4.0", 
            "rel": {
                "@id": "/r/AtLocation", 
                "@type": "Relation", 
                "label": "AtLocation"
            }, 
            "sources": [
                {
                    "@id": "/and/[/s/activity/omcs/omcs1_possibly_free_text/,/s/contributor/omcs/anaitis/]", 
                    "@type": "Source", 
                    "activity": "/s/activity/omcs/omcs1_possibly_free_text", 
                    "contributor": "/s/contributor/omcs/anaitis"
                }, 
                {
                    "@id": "/and/[/s/activity/omcs/vote/,/s/contributor/omcs/guru1/]", 
                    "@type": "Source", 
                    "activity": "/s/activity/omcs/vote", 
                    "contributor": "/s/contributor/omcs/guru1"
                }
            ], 
            "start": {
                "@id": "/c/en/umbrella", 
                "@type": "Node", 
                "label": "an umbrella", 
                "language": "en", 
                "term": "/c/en/umbrella"
            }, 
            "surfaceText": "You are likely to find [[an umbrella]] in [[an umbrella stand]]", 
            "weight": 2.0
        }
    ]
}